<annotation>
  <folder>images</folder>
  <filename>362.png</filename>
  <path>../images/362.png</path>
  <source>
    <database>Unknown</database>
  </source>
  <size>
    <width>499</width>
    <height>666</height>
    <depth>3</depth>
  </size>
  <segmented>0</segmented>
  <object>
    <name>NO</name>
    <pose>Unspecified</pose>
    <truncated>0</truncated>
    <difficult>0</difficult>
    <bndbox>
      <xmin>188</xmin>
      <ymin>0</ymin>
      <xmax>202</xmax>
      <ymax>15</ymax>
    </bndbox>
  </object>
  <object>
    <name>NO</name>
    <pose>Unspecified</pose>
    <truncated>0</truncated>
    <difficult>0</difficult>
    <bndbox>
      <xmin>273</xmin>
      <ymin>0</ymin>
      <xmax>288</xmax>
      <ymax>15</ymax>
    </bndbox>
  </object>
  <object>
    <name>YES</name>
    <pose>Unspecified</pose>
    <truncated>0</truncated>
    <difficult>0</difficult>
    <bndbox>
      <xmin>369</xmin>
      <ymin>0</ymin>
      <xmax>383</xmax>
      <ymax>15</ymax>
    </bndbox>
  </object>
  <object>
    <name>NO</name>
    <pose>Unspecified</pose>
    <truncated>0</truncated>
    <difficult>0</difficult>
    <bndbox>
      <xmin>188</xmin>
      <ymin>24</ymin>
      <xmax>202</xmax>
      <ymax>45</ymax>
    </bndbox>
  </object>
  <object>
    <name>NO</name>
    <pose>Unspecified</pose>
    <truncated>0</truncated>
    <difficult>0</difficult>
    <bndbox>
      <xmin>388</xmin>
      <ymin>24</ymin>
      <xmax>402</xmax>
      <ymax>45</ymax>
    </bndbox>
  </object>
</annotation>
