<annotation>
  <folder>images</folder>
  <filename>411.png</filename>
  <path>../images/411.png</path>
  <source>
    <database>Unknown</database>
  </source>
  <size>
    <width>499</width>
    <height>666</height>
    <depth>3</depth>
  </size>
  <segmented>0</segmented>
  <object>
    <name>YES</name>
    <pose>Unspecified</pose>
    <truncated>0</truncated>
    <difficult>0</difficult>
    <bndbox>
      <xmin>206</xmin>
      <ymin>4</ymin>
      <xmax>222</xmax>
      <ymax>24</ymax>
    </bndbox>
  </object>
  <object>
    <name>YES</name>
    <pose>Unspecified</pose>
    <truncated>0</truncated>
    <difficult>0</difficult>
    <bndbox>
      <xmin>301</xmin>
      <ymin>4</ymin>
      <xmax>317</xmax>
      <ymax>24</ymax>
    </bndbox>
  </object>
  <object>
    <name>NO</name>
    <pose>Unspecified</pose>
    <truncated>0</truncated>
    <difficult>0</difficult>
    <bndbox>
      <xmin>406</xmin>
      <ymin>4</ymin>
      <xmax>422</xmax>
      <ymax>24</ymax>
    </bndbox>
  </object>
  <object>
    <name>NO</name>
    <pose>Unspecified</pose>
    <truncated>0</truncated>
    <difficult>0</difficult>
    <bndbox>
      <xmin>206</xmin>
      <ymin>32</ymin>
      <xmax>222</xmax>
      <ymax>52</ymax>
    </bndbox>
  </object>
  <object>
    <name>NO</name>
    <pose>Unspecified</pose>
    <truncated>0</truncated>
    <difficult>0</difficult>
    <bndbox>
      <xmin>427</xmin>
      <ymin>32</ymin>
      <xmax>443</xmax>
      <ymax>52</ymax>
    </bndbox>
  </object>
</annotation>
