<annotation>
  <folder>images</folder>
  <filename>499.png</filename>
  <path>../images/499.png</path>
  <source>
    <database>Unknown</database>
  </source>
  <size>
    <width>499</width>
    <height>666</height>
    <depth>3</depth>
  </size>
  <segmented>0</segmented>
  <object>
    <name>YES</name>
    <pose>Unspecified</pose>
    <truncated>0</truncated>
    <difficult>0</difficult>
    <bndbox>
      <xmin>230</xmin>
      <ymin>0</ymin>
      <xmax>247</xmax>
      <ymax>23</ymax>
    </bndbox>
  </object>
  <object>
    <name>YES</name>
    <pose>Unspecified</pose>
    <truncated>0</truncated>
    <difficult>0</difficult>
    <bndbox>
      <xmin>334</xmin>
      <ymin>0</ymin>
      <xmax>352</xmax>
      <ymax>23</ymax>
    </bndbox>
  </object>
  <object>
    <name>NO</name>
    <pose>Unspecified</pose>
    <truncated>0</truncated>
    <difficult>0</difficult>
    <bndbox>
      <xmin>450</xmin>
      <ymin>0</ymin>
      <xmax>468</xmax>
      <ymax>23</ymax>
    </bndbox>
  </object>
  <object>
    <name>NO</name>
    <pose>Unspecified</pose>
    <truncated>0</truncated>
    <difficult>0</difficult>
    <bndbox>
      <xmin>230</xmin>
      <ymin>32</ymin>
      <xmax>247</xmax>
      <ymax>56</ymax>
    </bndbox>
  </object>
  <object>
    <name>YES</name>
    <pose>Unspecified</pose>
    <truncated>0</truncated>
    <difficult>0</difficult>
    <bndbox>
      <xmin>473</xmin>
      <ymin>32</ymin>
      <xmax>491</xmax>
      <ymax>56</ymax>
    </bndbox>
  </object>
</annotation>
